dockeree/__init__.py
dockeree/builder.py
dockeree/image.py
dockeree/node.py
dockeree/utils.py
dockeree-0.7.0.dist-info/METADATA
dockeree-0.7.0.dist-info/WHEEL
dockeree-0.7.0.dist-info/RECORD
