Metadata-Version: 2.4
Name: dockeree
Version: 0.7.0
Summary: Make it easy to build and manager Docker images.
Project-URL: Repository, https://github.com/legendu-net/dockeree
Author-email: Benjamin Du <longendu@yahoo.com>
License: GPL-2.0-only
Keywords: Docker,build,container,management
Requires-Python: <4,>=3.10
Requires-Dist: docker>=6.1.0
Requires-Dist: loguru>=0.6.0
Requires-Dist: networkx>=2.5
Requires-Dist: pandas>=1.2.0
Requires-Dist: pygit2>=1.9.1
Requires-Dist: pytest>=3.0
Requires-Dist: pyyaml>=6.0
